user_comments/__init__.py
user_comments/models.py
user_comments/contrib/__init__.py
user_comments/contrib/is_core/__init__.py
user_comments/contrib/is_core/cores.py
user_comments/locale/cs/LC_MESSAGES/django.mo
user_comments/locale/cs/LC_MESSAGES/django.po
user_comments/migrations/0001_initial.py
user_comments/migrations/0002_migration.py
user_comments/migrations/__init__.py
skip_django_user_comments-0.1.0.dist-info/METADATA
skip_django_user_comments-0.1.0.dist-info/WHEEL
skip_django_user_comments-0.1.0.dist-info/top_level.txt
skip_django_user_comments-0.1.0.dist-info/RECORD
