Metadata-Version: 2.1
Name: skip-django-user-comments
Version: 0.1.0
Summary: Library for adding comments of users related with object
Author: Lubos Matl
Author-email: matllubos@gmail.com
Requires-Dist: skip-django-chamber >=0.7.2
